openapi_typed/__init__.py
openapi_typed/openapi.py
openapi_typed/py.typed
openapi_typed-0.1.0.dist-info/LICENSE
openapi_typed-0.1.0.dist-info/METADATA
openapi_typed-0.1.0.dist-info/WHEEL
openapi_typed-0.1.0.dist-info/top_level.txt
openapi_typed-0.1.0.dist-info/RECORD
